lazylinop/__init__.py
lazylinop/check_op.py
lazylinop/lazylinop.py
lazylinop/basicops/__init__.py
lazylinop/basicops/add.py
lazylinop/basicops/anti_diag.py
lazylinop/basicops/anti_eye.py
lazylinop/basicops/bitrev.py
lazylinop/basicops/blockdiag.py
lazylinop/basicops/cat.py
lazylinop/basicops/diag.py
lazylinop/basicops/diff.py
lazylinop/basicops/eye.py
lazylinop/basicops/flip.py
lazylinop/basicops/kron.py
lazylinop/basicops/ones.py
lazylinop/basicops/pad.py
lazylinop/basicops/padder.py
lazylinop/basicops/roll.py
lazylinop/basicops/slicer.py
lazylinop/basicops/tri.py
lazylinop/basicops/zeros.py
lazylinop/butterfly/GB_factorization.py
lazylinop/butterfly/GB_utils.py
lazylinop/butterfly/__init__.py
lazylinop/butterfly/chain.py
lazylinop/butterfly/dft.py
lazylinop/butterfly/fuse.py
lazylinop/butterfly/hadamard.py
lazylinop/butterfly/ksd.py
lazylinop/butterfly/ksm.py
lazylinop/butterfly/kernels/template_bitrev_perm.clh
lazylinop/butterfly/kernels/template_bitrev_perm.cuh
lazylinop/butterfly/kernels/template_ksmm.clh
lazylinop/butterfly/kernels/template_ksmm.cuh
lazylinop/linalg/__init__.py
lazylinop/linalg/svds.py
lazylinop/polynomial/__init__.py
lazylinop/polynomial/polynomial.py
lazylinop/signal/__init__.py
lazylinop/signal/convolve.py
lazylinop/signal/dct.py
lazylinop/signal/dst.py
lazylinop/signal/dwt.py
lazylinop/signal/dzt.py
lazylinop/signal/fft.py
lazylinop/signal/fwht.py
lazylinop/signal/idwt.py
lazylinop/signal/imdct.py
lazylinop/signal/istft.py
lazylinop/signal/mdct.py
lazylinop/signal/nufft.py
lazylinop/signal/stft.py
lazylinop/signal/utils.py
lazylinop/signal2d/__init__.py
lazylinop/signal2d/convolve2d.py
lazylinop/signal2d/dct2d.py
lazylinop/signal2d/dst2d.py
lazylinop/signal2d/dwt2d.py
lazylinop/signal2d/fft2d.py
lazylinop/signal2d/flatten.py
lazylinop/signal2d/idwt2d.py
lazylinop/signal2d/mdct2d.py
lazylinop/signal2d/padder2d.py
lazylinop/utils/__init__.py
lazylinop/utils/utils.py
lazylinop/wip/__init__.py
lazylinop/wip/code_optimization.py
lazylinop-1.20.10.dist-info/METADATA
lazylinop-1.20.10.dist-info/WHEEL
lazylinop-1.20.10.dist-info/licenses/AUTHORS.md
lazylinop-1.20.10.dist-info/licenses/LICENSE.txt
lazylinop-1.20.10.dist-info/RECORD
