Metadata-Version: 2.4
Name: lazylinop
Version: 1.20.10
Summary: A package dedicated to lazy linear operators based on diverse backends/libraries.
Project-URL: Homepage, https://faustgrp.gitlabpages.inria.fr/lazylinop/
Project-URL: Documentation, https://faustgrp.gitlabpages.inria.fr/lazylinop/api.html
Project-URL: Repository, https://gitlab.inria.fr/faustgrp/lazylinop
Project-URL: Bug Tracker, https://gitlab.inria.fr/faustgrp/lazylinop/-/issues
Author-email: Inria <remi.gribonval@inria.fr>, Pascal Carrivain <pascal.carrivain@inria.fr>, Simon Delamare <simon.delamare@ens-lyon.fr>, Hakim Hadj-Djilani <hakim.hadj-djilani@inria.fr>, Rémi Gribonval <remi.gribonval@inria.fr>
License-Expression: BSD-2-Clause
License-File: AUTHORS.md
License-File: LICENSE.txt
Keywords: butterfly,lazy computation,signal processing
Classifier: Operating System :: OS Independent
Classifier: Programming Language :: Python :: 3
Requires-Python: >=3.10
Requires-Dist: array-api-compat>=1.12.0
Requires-Dist: numpy>=2.0
Requires-Dist: scipy>=1.13
Requires-Dist: sympy>=1.14
